<?xml version="1.0" encoding="UTF-8"?>
<!DOCTYPE hibernate-reverse-engineering 
  SYSTEM "http://hibernate.sourceforge.net/hibernate-reverse-engineering-3.0.dtd" >

<hibernate-reverse-engineering>

	<schema-selection match-schema="frotasweb" />

	<type-mapping>
		<sql-type jdbc-type="TINYINT" hibernate-type="java.lang.Integer" />
		<sql-type jdbc-type="BIGINT" hibernate-type="java.lang.Long" />
	</type-mapping>

	<table-filter match-name="jbpm_.*" exclude="true" />
	<table-filter match-name=".*">
		<meta attribute="extends">br.com.linkdata.entity.Entity</meta>
	</table-filter>

<!-- RELAÇÃO DE TABELAS ####################################################################### -->
	<table name="abrangencia">
		<meta attribute="extends">br.com.linkdata.domain.ElementoDeDominio</meta>
	</table>
	<table name="agregacao_indice">
		<meta attribute="extends">br.com.linkdata.domain.ElementoDeDominio</meta>
	</table>
	<table name="alerta_email_frotas">
		<meta attribute="extends">br.com.linkdata.entity.ExclusaoLogica</meta>
		<column name="email_usuario" property="email" />
		<column name="nm_usuario" property="nome" />
	</table>
	<table name="alerta_servico">
		<column name="vl_porcentagem_alerta_servico" property="porcentagem" />
		<column name="vl_km_referenciada" property="quilometragemReferenciada" />
	</table>
	<table name="amparo_legal">
		<foreign-key constraint-name="fk_amparolegalfilhos_al">
			<many-to-one property="amparoLegalPai" />
			<set property="amparosLegaisFilhos" />
		</foreign-key>
	</table>
<!-- FIM RELAÇÃO DE TABELAS ################################################################### -->
</hibernate-reverse-engineering>
