<?xml version="1.0"?>
<!DOCTYPE hibernate-mapping PUBLIC "-//Hibernate/Hibernate Mapping DTD 3.0//EN"
"http://hibernate.sourceforge.net/hibernate-mapping-3.0.dtd">
<!-- Generated 23/12/2009 11:50:13 by Hibernate Tools 3.2.5.Beta -->
<hibernate-mapping>
    <joined-subclass name="br.com.linkdata.entity.UsuarioFuncionario" extends="br.com.linkdata.entity.Usuario" table="USUARIO_FUNCIONARIO">
        <key>
            <column name="USUARIO_ID" not-null="true" />
        </key>
        <many-to-one name="funcionario" class="br.com.linkdata.entity.Funcionario" access="field" fetch="join">
            <column name="ID_FUNCIONARIO" />
        </many-to-one>
    </joined-subclass>
</hibernate-mapping>
